idds/__init__.py
idds/website/__init__.py
idds/website/version.py
idds_website-2.0.9.data/data/website/data/index.html
idds_website-2.0.9.data/data/website/data/assets/css/font-awesome.min.css
idds_website-2.0.9.data/data/website/data/assets/css/main.css
idds_website-2.0.9.data/data/website/data/assets/fonts/FontAwesome.otf
idds_website-2.0.9.data/data/website/data/assets/fonts/fontawesome-webfont.eot
idds_website-2.0.9.data/data/website/data/assets/fonts/fontawesome-webfont.svg
idds_website-2.0.9.data/data/website/data/assets/fonts/fontawesome-webfont.ttf
idds_website-2.0.9.data/data/website/data/assets/fonts/fontawesome-webfont.woff
idds_website-2.0.9.data/data/website/data/assets/fonts/fontawesome-webfont.woff2
idds_website-2.0.9.data/data/website/data/assets/js/jquery.min.js
idds_website-2.0.9.data/data/website/data/assets/js/jquery.scrollex.min.js
idds_website-2.0.9.data/data/website/data/assets/js/main.js
idds_website-2.0.9.data/data/website/data/assets/js/skel.min.js
idds_website-2.0.9.data/data/website/data/assets/js/util.js
idds_website-2.0.9.data/data/website/data/images/bg.jpg
idds_website-2.0.9.data/data/website/data/images/idds.png
idds_website-2.0.9.data/data/website/data/images/idds_architecture.png
idds_website-2.0.9.data/data/website/data/images/idds_components.png
idds_website-2.0.9.data/data/website/data/images/idds_delivery.jpg
idds_website-2.0.9.data/data/website/data/images/idds_full.jpg
idds_website-2.0.9.data/data/website/data/images/idds_intelligent.jpg
idds_website-2.0.9.data/data/website/data/images/idds_main.jpg
idds_website-2.0.9.data/data/website/data/images/idds_orchestration.jpg
idds_website-2.0.9.data/data/website/data/images/idds_transform.jpg
idds_website-2.0.9.data/data/website/data/images/images.jpg
idds_website-2.0.9.data/data/website/data/images/pic01.jpg
idds_website-2.0.9.data/data/website/data/images/pic02.jpg
idds_website-2.0.9.data/data/website/data/images/pic03.jpg
idds_website-2.0.9.dist-info/LICENSE.rst
idds_website-2.0.9.dist-info/METADATA
idds_website-2.0.9.dist-info/WHEEL
idds_website-2.0.9.dist-info/top_level.txt
idds_website-2.0.9.dist-info/RECORD
